borb/__init__.py
borb/pdf/__init__.py
borb/pdf/conformance.py
borb/pdf/document.py
borb/pdf/page.py
borb/pdf/page_size.py
borb/pdf/primitives.py
borb/pdf/table_of_contents.py
borb/pdf/color/__init__.py
borb/pdf/color/cmyk_color.py
borb/pdf/color/color.py
borb/pdf/color/color_scheme.py
borb/pdf/color/farrow_and_ball_color.py
borb/pdf/color/grayscale_color.py
borb/pdf/color/hex_color.py
borb/pdf/color/hsv_color.py
borb/pdf/color/pantone_color.py
borb/pdf/color/rgb_color.py
borb/pdf/color/x11_color.py
borb/pdf/document_layout/__init__.py
borb/pdf/document_layout/a4_portrait.py
borb/pdf/document_layout/a4_portrait_invoice.py
borb/pdf/document_layout/a4_portrait_resume.py
borb/pdf/document_layout/document_layout.py
borb/pdf/document_layout/slideshow.py
borb/pdf/font/__init__.py
borb/pdf/font/adobe_glyph_list.py
borb/pdf/font/cmap.py
borb/pdf/font/common_font_encondings.py
borb/pdf/font/font.py
borb/pdf/font/composite_font/__init__.py
borb/pdf/font/composite_font/cid_type_0_font.py
borb/pdf/font/composite_font/composite_font.py
borb/pdf/font/simple_font/__init__.py
borb/pdf/font/simple_font/simple_font.py
borb/pdf/font/simple_font/standard_14_fonts.py
borb/pdf/font/simple_font/standard_type_1_font.py
borb/pdf/font/simple_font/type_1_font.py
borb/pdf/font/simple_font/courier/__init__.py
borb/pdf/font/simple_font/courier/courier.py
borb/pdf/font/simple_font/courier/courier_bold.py
borb/pdf/font/simple_font/courier/courier_bold_italic.py
borb/pdf/font/simple_font/courier/courier_italic.py
borb/pdf/font/simple_font/helvetica/__init__.py
borb/pdf/font/simple_font/helvetica/helvetica.py
borb/pdf/font/simple_font/helvetica/helvetica_bold.py
borb/pdf/font/simple_font/helvetica/helvetica_bold_italic.py
borb/pdf/font/simple_font/helvetica/helvetica_italic.py
borb/pdf/font/simple_font/symbol/__init__.py
borb/pdf/font/simple_font/symbol/symbol.py
borb/pdf/font/simple_font/times/__init__.py
borb/pdf/font/simple_font/times/times.py
borb/pdf/font/simple_font/times/times_bold.py
borb-3.0.5.dist-info/licenses/LICENSE.md
borb-3.0.5.dist-info/METADATA
borb-3.0.5.dist-info/WHEEL
borb-3.0.5.dist-info/top_level.txt
borb-3.0.5.dist-info/RECORD
