Metadata-Version: 2.4
Name: borb
Version: 3.0.5
Summary: borb is a library for reading, creating and manipulating PDF files in python.
Home-page: https://github.com/jorisschellekens/borb
Author: Joris Schellekens
Author-email: joris.schellekens.1989@gmail.com
Requires-Python: >=3.6
License-File: LICENSE.md
Requires-Dist: setuptools>=51.1.1
Dynamic: author
Dynamic: author-email
Dynamic: description
Dynamic: description-content-type
Dynamic: home-page
Dynamic: license-file
Dynamic: requires-dist
Dynamic: requires-python
Dynamic: summary
